authemail/__init__.py
authemail/admin.py
authemail/forms.py
authemail/models.py
authemail/serializers.py
authemail/tests.py
authemail/urls.py
authemail/views.py
authemail/wrapper.py
authemail/locale/fr/LC_MESSAGES/django.mo
authemail/locale/fr/LC_MESSAGES/django.po
authemail/locale/id/LC_MESSAGES/django.mo
authemail/locale/id/LC_MESSAGES/django.po
authemail/migrations/0001_initial.py
authemail/migrations/0002_emailchangecode.py
authemail/migrations/__init__.py
authemail/templates/authemail/email_change_confirm_new_email.html
authemail/templates/authemail/email_change_confirm_new_email.txt
authemail/templates/authemail/email_change_confirm_new_email_subject.txt
authemail/templates/authemail/email_change_notify_previous_email.html
authemail/templates/authemail/email_change_notify_previous_email.txt
authemail/templates/authemail/email_change_notify_previous_email_subject.txt
authemail/templates/authemail/password_reset_email.html
authemail/templates/authemail/password_reset_email.txt
authemail/templates/authemail/password_reset_email_subject.txt
authemail/templates/authemail/signup_email.html
authemail/templates/authemail/signup_email.txt
authemail/templates/authemail/signup_email_subject.txt
authemail/templates/authemail/welcome_email.html
authemail/templates/authemail/welcome_email.txt
authemail/templates/authemail/welcome_email_subject.txt
django_rest_authemail-2.1.7.dist-info/LICENSE
django_rest_authemail-2.1.7.dist-info/METADATA
django_rest_authemail-2.1.7.dist-info/WHEEL
django_rest_authemail-2.1.7.dist-info/top_level.txt
django_rest_authemail-2.1.7.dist-info/RECORD
