Metadata-Version: 2.1
Name: django-rest-authemail
Version: 2.1.7
Summary: A RESTful API for user signup and authentication using email addresses
Home-page: http://github.com/celiao/django-rest-authemail
Download-URL: https://github.com/celiao/django-rest-authemail/tarball/2.1.7
Author: Celia Oakley
Author-email: celia.oakley@alumni.stanford.edu
Keywords: django,python,rest,rest-framework,api,auth,authentication,email,user,username,registration,signup,login,logout,password,django-rest-framework,djangorestframework,django-registration,django-email-as-username
Classifier: Development Status :: 5 - Production/Stable
Classifier: Environment :: Web Environment
Classifier: Framework :: Django :: 2.2
Classifier: Framework :: Django :: 3.0
Classifier: Framework :: Django :: 3.1
Classifier: Framework :: Django :: 3.2
Classifier: Intended Audience :: Developers
Classifier: Natural Language :: English
Classifier: Operating System :: OS Independent
Classifier: Programming Language :: Python :: 3.6
Classifier: Programming Language :: Python :: 3.7
Classifier: Programming Language :: Python :: 3.8
Classifier: Topic :: Internet :: WWW/HTTP
Classifier: Topic :: Software Development
Classifier: Topic :: Utilities
License-File: LICENSE
